{"packages/cupertino_icons/assets/CupertinoIcons.ttf":["packages/cupertino_icons/assets/CupertinoIcons.ttf"],"assets/app_diagram.png":["assets/app_diagram.png"],"assets/bg.jpg":["assets/bg.jpg"],"assets/corodova_logo.png":["assets/corodova_logo.png"],"assets/dart_logo.png":["assets/dart_logo.png"],"assets/flow_diagram.png":["assets/flow_diagram.png"],"assets/flutter_flow.png":["assets/flutter_flow.png"],"assets/heart.png":["assets/heart.png"],"assets/ionic_logo.png":["assets/ionic_logo.png"],"assets/logo.png":["assets/logo.png"],"assets/logo2.png":["assets/logo2.png"],"assets/phonegap_logo.png":["assets/phonegap_logo.png"],"assets/react_native_flow.png":["assets/react_native_flow.png"],"assets/react_native_logo.png":["assets/react_native_logo.png"],"assets/stack_logo.png":["assets/stack_logo.png"],"assets/stack_loved.png":["assets/stack_loved.png"],"assets/web_view.png":["assets/web_view.png"]}